<?xml version="1.0" encoding="UTF-8" standalone="yes"?>
<APIProxy revision="1" name="EdgeDeveloper-Visitor-Sample">
    <ConfigurationVersion majorVersion="4" minorVersion="0"/>
    <CreatedAt>1429068994924</CreatedAt>
    <CreatedBy>kkleva@llbean.com</CreatedBy>
    <Description>Edge Developer Visitor API Target</Description>
    <DisplayName>EdgeDeveloper-Visitor-Sample</DisplayName>
    <LastModifiedAt>1429069181435</LastModifiedAt>
    <LastModifiedBy>kkleva@llbean.com</LastModifiedBy>
    <Policies/>
    <ProxyEndpoints>
        <ProxyEndpoint>default</ProxyEndpoint>
    </ProxyEndpoints>
    <Resources>
        <Resource>node://package.json</Resource>
        <Resource>node://server-usergrid.js</Resource>
    </Resources>
    <TargetServers/>
    <TargetEndpoints>
        <TargetEndpoint>default</TargetEndpoint>
    </TargetEndpoints>
    <validate>false</validate>
</APIProxy>
